googlemap/__init__.py
wsdotnet-0.1.0.dist-info/METADATA
wsdotnet-0.1.0.dist-info/WHEEL
wsdotnet-0.1.0.dist-info/top_level.txt
wsdotnet-0.1.0.dist-info/RECORD
