Metadata-Version: 2.4
Name: wsdotnet
Version: 0.1.0
Summary: Define a simple service like Converting Rs into Dollar and Call it from different platform like JAVA and .NET
Author: Aryan Bhagwat
Author-email: legendasur531@gmail.com
Classifier: Programming Language :: Python :: 3
Classifier: Operating System :: OS Independent
Requires-Python: >=3.6
Dynamic: author
Dynamic: author-email
Dynamic: classifier
Dynamic: requires-python
Dynamic: summary
